AUTHORS.md
HISTORY.md
LICENSE
minos/api_gateway/rest/__init__.py
minos/api_gateway/rest/__main__.py
minos/api_gateway/rest/backend/admin/3rdpartylicenses.txt
minos/api_gateway/rest/backend/admin/assets/images/minos_color@2x.png
minos/api_gateway/rest/backend/admin/color.dae87a04d07ca92b.png
minos/api_gateway/rest/backend/admin/favicon.ico
minos/api_gateway/rest/backend/admin/hue.8b1818380241e6ac.png
minos/api_gateway/rest/backend/admin/main.33051811e0a291cf.js
minos/api_gateway/rest/backend/admin/main.727c29f160d3bc80.js
minos/api_gateway/rest/backend/admin/polyfills.cacc82dae5605706.js
minos/api_gateway/rest/backend/admin/primeicons.29151a741d66863a.woff
minos/api_gateway/rest/backend/admin/primeicons.5f5d08cd089b4e5d.ttf
minos/api_gateway/rest/backend/admin/primeicons.76044b1c189cc4d7.svg
minos/api_gateway/rest/backend/admin/primeicons.964f445f3ea9db80.eot
minos/api_gateway/rest/backend/admin/runtime.3586ab90ea013581.js
minos/api_gateway/rest/backend/admin/styles.ee7401a7ef5a34ac.css
minos/api_gateway/rest/backend/templates/index.html
minos/api_gateway/rest/cli.py
minos/api_gateway/rest/config.py
minos/api_gateway/rest/database/models.py
minos/api_gateway/rest/database/repository.py
minos/api_gateway/rest/exceptions.py
minos/api_gateway/rest/handler.py
minos/api_gateway/rest/launchers.py
minos/api_gateway/rest/service.py
minos/api_gateway/rest/urlmatch/__init__.py
minos/api_gateway/rest/urlmatch/authmatch.py
minos/api_gateway/rest/urlmatch/autzmatch.py
minos/api_gateway/rest/urlmatch/urlmatch.py
minos_apigateway-0.4.0.dist-info/entry_points.txt
minos_apigateway-0.4.0.dist-info/LICENSE
minos_apigateway-0.4.0.dist-info/WHEEL
minos_apigateway-0.4.0.dist-info/METADATA
minos_apigateway-0.4.0.dist-info/RECORD
