Metadata-Version: 2.1
Name: minos-apigateway
Version: 0.4.0
Summary: Python Package containing the main API Gateway implementation used in Minos Microservices.
Home-page: https://clariteia.com
License: MIT
Keywords: clariteia,minos,microservice,api_gateway
Author: Clariteia Devs
Author-email: devs@clariteia.com
Requires-Python: >=3.9,<4.0
Classifier: Development Status :: 2 - Pre-Alpha
Classifier: Intended Audience :: Developers
Classifier: License :: OSI Approved :: MIT License
Classifier: Natural Language :: English
Classifier: Programming Language :: Python :: 3
Classifier: Programming Language :: Python :: 3.9
Requires-Dist: PyYAML (>=6.0,<7.0)
Requires-Dist: SQLAlchemy (==1.4.22)
Requires-Dist: aiohttp (>=3.8.1,<4.0.0)
Requires-Dist: aiohttp-jinja2 (>=1.5,<2.0)
Requires-Dist: aiohttp-middlewares (>=1.2.1,<2.0.0)
Requires-Dist: aiomisc (>=15.2.16,<16.0.0)
Requires-Dist: cached-property (>=1.5.2,<2.0.0)
Requires-Dist: psycopg2 (>=2.9.3,<3.0.0)
Requires-Dist: typer (>=0.3.2,<0.4.0)
Project-URL: Repository, https://github.com/clariteia/api_gateway
